odoo/addons/stock_account_internal_move/README.rst
odoo/addons/stock_account_internal_move/__init__.py
odoo/addons/stock_account_internal_move/__manifest__.py
odoo/addons/stock_account_internal_move/i18n/stock_account_internal_move.pot
odoo/addons/stock_account_internal_move/i18n/zh_CN.po
odoo/addons/stock_account_internal_move/models/__init__.py
odoo/addons/stock_account_internal_move/models/stock_location.py
odoo/addons/stock_account_internal_move/models/stock_move.py
odoo/addons/stock_account_internal_move/readme/CONFIGURE.rst
odoo/addons/stock_account_internal_move/readme/CONTRIBUTORS.rst
odoo/addons/stock_account_internal_move/readme/DESCRIPTION.rst
odoo/addons/stock_account_internal_move/readme/USAGE.rst
odoo/addons/stock_account_internal_move/static/description/icon.png
odoo/addons/stock_account_internal_move/static/description/index.html
odoo/addons/stock_account_internal_move/tests/__init__.py
odoo/addons/stock_account_internal_move/tests/test_stock_move_confirmation.py
odoo/addons/stock_account_internal_move/views/stock_location.xml
odoo12_addon_stock_account_internal_move-12.0.1.0.0.99.dev10.dist-info/METADATA
odoo12_addon_stock_account_internal_move-12.0.1.0.0.99.dev10.dist-info/WHEEL
odoo12_addon_stock_account_internal_move-12.0.1.0.0.99.dev10.dist-info/top_level.txt
odoo12_addon_stock_account_internal_move-12.0.1.0.0.99.dev10.dist-info/RECORD
